Metadata-Version: 2.4
Name: raichu
Version: 1.0.4
Summary: RAIChU
Author: Barbara Terlouw
Author-email: barbara.r.terlouw@gmail.com
Requires-Python: >=3.7, <3.10
License-File: LICENSE.txt
Requires-Dist: matplotlib
Requires-Dist: biopython==1.83
Requires-Dist: pikachu-chem>=1.1.4
Requires-Dist: timeout-decorator
Dynamic: author
Dynamic: author-email
Dynamic: description
Dynamic: license-file
Dynamic: requires-dist
Dynamic: requires-python
Dynamic: summary
